srp6/__init__.py
srp6/client.py
srp6/constants.py
srp6/hashcash.py
srp6/utils.py
srp6-0.1.1.dist-info/METADATA
srp6-0.1.1.dist-info/WHEEL
srp6-0.1.1.dist-info/licenses/LICENSE
srp6-0.1.1.dist-info/RECORD
