Metadata-Version: 2.4
Name: srp6
Version: 0.1.1
Summary: Pure Python SRP-6a client implementation with GSA mode support
Project-URL: Homepage, https://github.com/bigbag/srp6
Project-URL: Repository, https://github.com/bigbag/srp6
Project-URL: Issues, https://github.com/bigbag/srp6/issues
Author-email: Pavel Liashkov <pavel.liashkov@protonmail.com>
License-Expression: MIT
License-File: LICENSE
Keywords: authentication,cryptography,secure-remote-password,srp,srp6,srp6a
Classifier: Development Status :: 4 - Beta
Classifier: License :: OSI Approved :: MIT License
Classifier: Programming Language :: Python :: 3
Classifier: Programming Language :: Python :: 3.10
Classifier: Programming Language :: Python :: 3.11
Classifier: Programming Language :: Python :: 3.12
Classifier: Programming Language :: Python :: 3.13
Classifier: Programming Language :: Python :: 3.14
Classifier: Topic :: Security :: Cryptography
Classifier: Topic :: Software Development :: Libraries :: Python Modules
Requires-Python: >=3.10
